Metadata-Version: 1.0
Name: opacity-calculator
Version: 0.1
Summary: Calculating opacities
Home-page: https://github.com/bldevries/opacity_calculator
Author: B.L. de Vries
Author-email: bldevries.science@gmail.com
License: UNKNOWN
Platform: UNKNOWN
